bin/stecMenu.py
bin/stecMenuBuilder.py
stdcomMenu/__init__.py
stdcomMenu/builder.py
stdcomMenu/config.py
stdcomMenu/menu.py
stdcomMenu/stdcOperator.py
stdcomMenu/stdmenu.py
stdcomMenu-1.1.1.dist-info/LICENSE.txt
stdcomMenu-1.1.1.dist-info/METADATA
stdcomMenu-1.1.1.dist-info/WHEEL
stdcomMenu-1.1.1.dist-info/top_level.txt
stdcomMenu-1.1.1.dist-info/RECORD
