Metadata-Version: 2.1
Name: stdcomMenu
Version: 1.1.1
Summary: Stec Railway Version StandAlone Subscribers
Home-page: http://www.vremsoft.com
Author: ed
Author-email: srini_durand@yahoo.com
License: UNKNOWN
Platform: UNKNOWN
Classifier: Programming Language :: Python :: 3
Classifier: Programming Language :: Python :: 3.5
Classifier: Programming Language :: Python :: 3.6
Classifier: Programming Language :: Python :: 3.7
Classifier: Programming Language :: Python :: 3.8
Classifier: Programming Language :: Python :: 3.9
Classifier: Programming Language :: Python :: 3.10
Classifier: License :: OSI Approved :: GNU General Public License v3 or later (GPLv3+)
Classifier: Operating System :: OS Independent
Requires: setuptools
Requires: wheel
Requires: PyQt5
License-File: LICENSE.txt
Requires-Dist: PyQt5
